qconduit/__init__.py
qconduit/adiabatic/__init__.py
qconduit/adiabatic/evolution.py
qconduit/adiabatic/schedules.py
qconduit/algorithms/__init__.py
qconduit/algorithms/qaoa.py
qconduit/algorithms/vqe.py
qconduit/backend/__init__.py
qconduit/backend/density_matrix.py
qconduit/backend/statevector.py
qconduit/circuit/__init__.py
qconduit/circuit/core.py
qconduit/core/__init__.py
qconduit/core/device.py
qconduit/core/module.py
qconduit/diagnostics/__init__.py
qconduit/diagnostics/core.py
qconduit/diagnostics/debug_mode.py
qconduit/evolution/__init__.py
qconduit/evolution/exact.py
qconduit/evolution/trotter.py
qconduit/exact/__init__.py
qconduit/exact/diagonalize.py
qconduit/experiments/__init__.py
qconduit/experiments/sweep.py
qconduit/fermion/__init__.py
qconduit/fermion/mappings.py
qconduit/fermion/operators.py
qconduit/gates/__init__.py
qconduit/gates/standard.py
qconduit/grad/__init__.py
qconduit/grad/param_shift.py
qconduit/grad/parameter_shift.py
qconduit/layers/__init__.py
qconduit/layers/ansatzes.py
qconduit/layers/hybrid.py
qconduit/measurement/__init__.py
qconduit/measurement/sampling.py
qconduit/measurement/tomography.py
qconduit/models/__init__.py
qconduit/models/spin_chains.py
qconduit/models/toy_qubit_models.py
qconduit/noise/__init__.py
qconduit/noise/base.py
qconduit/noise/channels.py
qconduit/noise/density.py
qconduit/noise/kraus.py
qconduit/noise/noisy_circuit.py
qconduit/operators/__init__.py
qconduit/operators/expectation.py
qconduit/operators/pauli.py
qconduit/optim/__init__.py
qconduit/optim/factory.py
qconduit/sampling/__init__.py
qconduit/sampling/bitstrings.py
qconduit/sampling/hist.py
qconduit/time_evolution/__init__.py
qconduit/time_evolution/circuits.py
qconduit/time_evolution/core.py
qconduit/training/__init__.py
qconduit/training/vqe_training.py
qconduit/transpile/__init__.py
qconduit/transpile/analysis.py
qconduit/transpile/basis.py
qconduit/transpile/decompose.py
qconduit/variational/__init__.py
qconduit/variational/ansatz.py
qconduit-0.0.4.dist-info/licenses/LICENSE
qconduit-0.0.4.dist-info/METADATA
qconduit-0.0.4.dist-info/WHEEL
qconduit-0.0.4.dist-info/top_level.txt
qconduit-0.0.4.dist-info/RECORD
