Metadata-Version: 2.4
Name: qconduit
Version: 0.0.4
Summary: A PyTorch-native quantum statevector plumbing library for quantum machine learning
Author-email: Sean Simms <seansimms00@gmail.com>
Maintainer-email: Sean Simms <seansimms00@gmail.com>
License-Expression: MIT
Project-URL: Homepage, https://github.com/seansimms/Quantum_Conduit
Project-URL: Documentation, https://github.com/seansimms/Quantum_Conduit
Project-URL: Repository, https://github.com/seansimms/Quantum_Conduit
Project-URL: Bug Tracker, https://github.com/seansimms/Quantum_Conduit/issues
Project-URL: Zenodo DOI, https://doi.org/10.5281/zenodo.17599984
Keywords: quantum computing,quantum machine learning,pytorch,variational quantum algorithms,VQE,QAOA,quantum statevector,quantum simulation,quantum chemistry,quantum optimization
Classifier: Development Status :: 4 - Beta
Classifier: Intended Audience :: Science/Research
Classifier: Intended Audience :: Developers
Classifier: Operating System :: OS Independent
Classifier: Programming Language :: Python :: 3
Classifier: Programming Language :: Python :: 3.10
Classifier: Programming Language :: Python :: 3.11
Classifier: Programming Language :: Python :: 3.12
Classifier: Topic :: Scientific/Engineering :: Physics
Classifier: Topic :: Scientific/Engineering :: Artificial Intelligence
Classifier: Topic :: Software Development :: Libraries :: Python Modules
Requires-Python: >=3.10
License-File: LICENSE
Requires-Dist: torch>=2.1
Provides-Extra: dev
Requires-Dist: pytest>=7.0; extra == "dev"
Requires-Dist: ruff>=0.1.0; extra == "dev"
Requires-Dist: build>=1.0.0; extra == "dev"
Requires-Dist: twine>=4.0.0; extra == "dev"
Dynamic: license-file
